{
    "cards": [
      {
        "id": 1,
        "title": "Lanches",
        "description": "Lanches smash burgers, opções premium e os clássicos.",
        "image": "src/assets/img/logo1.png"
      },
      {
        "id": 2,
        "title": "Bebibas",
        "description": "Refrigerantes, sucos naturais e destilados",
        "image": "src/assets/img/logo1.png"
      },
      {
        "id": 3,
        "title": "Porções",
        "description": "Bata frita, onion rings, frango a passarinho e muito mais",
        "image": "src/assets/img/logo1.png"
      },
      {
        "id": 4,
        "title": "Sorvetes",
        "description": "Cremosos, refrescantes e irresistíveis.",
        "image": "src/assets/img/logo1.png"
      },
      {
        "id": 5,
        "title": "Churrasco",
        "description": "Sabor de brasa, feito no ponto certo.",
        "image": "src/assets/img/logo1.png"
      },
      {
        "id": 6,
        "title": "Marmita",
        "description": "Refeições caseiras, completas e saborosas.",
        "image": "src/assets/img/logo1.png"
      },
      {
        "id": 7,
        "title": "Espetinho",
        "description": "Assados na brasa, suculentos e bem temperados.",
        "image": "src/assets/img/logo1.png"
      },
      {
        "id": 8,
        "title": "Sobremesa",
        "description": "Doces perfeitos para fechar sua refeição.",
        "image": "src/assets/img/logo1.png"
      },
      {
        "id": 9,
        "title": "Pizza",
        "description": "Massa crocante, muito recheio e sabor incrível.",
        "image": "src/assets/img/logo1.png"
      }
    ]
  }
  